jk_pwdgen/AbstractCLICmd.py
jk_pwdgen/AbstractMultiCmdCLIApp.py
jk_pwdgen/AppColors.py
jk_pwdgen/AppRuntime.py
jk_pwdgen/CLIRunCtx.py
jk_pwdgen/IExitCodes.py
jk_pwdgen/PasswordGenerator.py
jk_pwdgen/__init__.py
jk_pwdgen/bin/cli_pwdgen.py
jk_pwdgen-0.2024.11.3.4.dist-info/entry_points.txt
jk_pwdgen-0.2024.11.3.4.dist-info/WHEEL
jk_pwdgen-0.2024.11.3.4.dist-info/METADATA
jk_pwdgen-0.2024.11.3.4.dist-info/RECORD
