Metadata-Version: 2.1
Name: jk_pwdgen
Version: 0.2024.11.3.4
Summary: This python module provides support for password generation.
Keywords: console,terminal,cli
Author-email: Jürgen Knauth <pubsrc@binary-overflow.de>
Maintainer-email: Jürgen Knauth <pubsrc@binary-overflow.de>
Requires-Python: >=3.8
Classifier: Development Status :: 5 - Production/Stable
Classifier: License :: OSI Approved :: Apache Software License
Classifier: Programming Language :: Python :: 3
Requires-Dist: jk_argparsing >= 0.2024.2.1
Requires-Dist: jk_typing >= 0.2024.1.3
Requires-Dist: jk_logging >= 0.2024.1.3
Requires-Dist: jk_console >= 0.2024.4.24
